getvista/__init__.py
getvista/config.ini
getvista/emailaddress.py
getvista/enspecies.py
getvista/envistacoords.py
getvista/envistagene.py
getvista/gbgenerecord.py
getvista/gbvistacoords.py
getvista/gbvistagene.py
getvista/version_check.py
getvista-0.7.1.dist-info/LICENSE
getvista-0.7.1.dist-info/METADATA
getvista-0.7.1.dist-info/WHEEL
getvista-0.7.1.dist-info/entry_points.txt
getvista-0.7.1.dist-info/top_level.txt
getvista-0.7.1.dist-info/RECORD
