Metadata-Version: 2.1
Name: getvista
Version: 0.7.1
Summary: A python package to quickly get FASTA and pipmaker annotation files from Ensembl or GenBank for use in mVISTA alignment analysis.
Home-page: 
Author: Jake Leyhr
Author-email: jakeleyhr535@gmail.com
Classifier: Programming Language :: Python :: 3
Classifier: Operating System :: OS Independent
Requires-Python: >=3.11
License-File: LICENSE
Requires-Dist: requests
Requires-Dist: packaging
Requires-Dist: biopython
Requires-Dist: configparser
Requires-Dist: fuzzywuzzy
Requires-Dist: python-Levenshtein
Provides-Extra: dev
Requires-Dist: pytest ; extra == 'dev'
Requires-Dist: black ; extra == 'dev'
Requires-Dist: setuptools ; extra == 'dev'
Requires-Dist: twine ; extra == 'dev'
